django_extended_history/__init__.py
django_extended_history/admin.py
django_extended_history/tests.py
django_extended_history/templates/object_history.html
django_extended_history/templates/admin/admin/change_form.html
django_extended_history-1.9.4.dist-info/LICENSE
django_extended_history-1.9.4.dist-info/METADATA
django_extended_history-1.9.4.dist-info/WHEEL
django_extended_history-1.9.4.dist-info/top_level.txt
django_extended_history-1.9.4.dist-info/RECORD
