Metadata-Version: 2.2
Name: django-extended-history
Version: 1.9.4
Summary: Drop-in replacement for default Django history
Home-page: https://github.com/HealthyFridge/django-extended-history
Author: Rob Aben
Author-email: rob@healthyfridge.nl
License: BSD-3-Clause
Project-URL: Bug Tracker, https://github.com/HealthyFridge/django-extended-history/issues
Project-URL: repository, https://github.com/HealthyFridge/django-extended-history
Classifier: Programming Language :: Python :: 3.8
Classifier: Programming Language :: Python :: 3.9
Classifier: Programming Language :: Python :: 3.10
Classifier: Programming Language :: Python :: 3.11
Classifier: Programming Language :: Python :: 3.12
Classifier: Programming Language :: Python :: 3.13
Classifier: Framework :: Django :: 4.2
Classifier: Framework :: Django :: 5.0
Classifier: Framework :: Django :: 5.1
Classifier: Framework :: Django :: 5.2
Classifier: License :: OSI Approved :: BSD License
Classifier: Operating System :: OS Independent
Classifier: Development Status :: 5 - Production/Stable
Requires-Python: >=3.8
License-File: LICENSE
Requires-Dist: django>=4.2
Requires-Dist: json2html>=1.3.0
